[
    {
        "white": "jared",
        "black": "ben",
        "details": "it's like an eric rosen video in here",
        "board": [
            [" ", " ", " ", " ", " ", "r", " ", " "],
            [" ", " ", "p", "k", " ", " ", "p", " "],
            ["p", " ", " ", " ", " ", " ", "N", "p"],
            [" ", "p", "b", "n", "p", " ", " ", " "],
            [" ", " ", "b", "n", " ", " ", " ", " "],
            ["P", " ", "K", " ", " ", "P", " ", "P"],
            [" ", "P", " ", "P", " ", " ", "P", " "],
            [" ", "B", "B", " ", " ", " ", " ", "R"]
        ]
    },
    {
        "white": "jared",
        "black": "ben",
        "details": "king lighter III",
        "board": [
            ["r", " ", " ", " ", " ", " ", " ", " "],
            [" ", " ", " ", " ", "Q", " ", " ", "p"],
            [" ", " ", " ", "p", " ", " ", "p", "k"],
            [" ", " ", " ", " ", "p", " ", " ", " "],
            [" ", " ", "P", " ", " ", " ", " ", " "],
            [" ", " ", " ", " ", " ", " ", " ", "R"],
            [" ", " ", "r", " ", " ", " ", " ", "P"],
            ["q", " ", " ", "N", "K", " ", " ", " "]
        ]
    },
    {
        "white": "",
        "black": "",
        "details": "new game",
        "board": [
            ["r", "n", "b", "q", "k", "b", "n", "r"],
            ["p", "p", "p", "p", "p", "p", "p", "p"],
            [" ", " ", " ", " ", " ", " ", " ", " "],
            [" ", " ", " ", " ", " ", " ", " ", " "],
            [" ", " ", " ", " ", " ", " ", " ", " "],
            [" ", " ", " ", " ", " ", " ", " ", " "],
            ["P", "P", "P", "P", "P", "P", "P", "P"],
            ["R", "N", "B", "Q", "K", "B", "N", "R"]
        ]
    },
    {
        "white": "",
        "black": "",
        "details": "new game",
        "board": [
            ["r", "n", "b", "q", "k", "b", "n", "r"],
            ["p", "p", "p", "p", "p", "p", "p", "p"],
            [" ", " ", " ", " ", " ", " ", " ", " "],
            [" ", " ", " ", " ", " ", " ", " ", " "],
            [" ", " ", " ", " ", " ", " ", " ", " "],
            [" ", " ", " ", " ", " ", " ", " ", " "],
            ["P", "P", "P", "P", "P", "P", "P", "P"],
            ["R", "N", "B", "Q", "K", "B", "N", "R"]
        ]
    },
    {
        "white": "",
        "black": "",
        "details": "new game",
        "board": [
            ["r", "n", "b", "q", "k", "b", "n", "r"],
            ["p", "p", "p", "p", "p", "p", "p", "p"],
            [" ", " ", " ", " ", " ", " ", " ", " "],
            [" ", " ", " ", " ", " ", " ", " ", " "],
            [" ", " ", " ", " ", " ", " ", " ", " "],
            [" ", " ", " ", " ", " ", " ", " ", " "],
            ["P", "P", "P", "P", "P", "P", "P", "P"],
            ["R", "N", "B", "Q", "K", "B", "N", "R"]
        ]
    },
    {
        "white": "",
        "black": "",
        "details": "new game",
        "board": [
            ["r", "n", "b", "q", "k", "b", "n", "r"],
            ["p", "p", "p", "p", "p", "p", "p", "p"],
            [" ", " ", " ", " ", " ", " ", " ", " "],
            [" ", " ", " ", " ", " ", " ", " ", " "],
            [" ", " ", " ", " ", " ", " ", " ", " "],
            [" ", " ", " ", " ", " ", " ", " ", " "],
            ["P", "P", "P", "P", "P", "P", "P", "P"],
            ["R", "N", "B", "Q", "K", "B", "N", "R"]
        ]
    },
    {
        "white": "",
        "black": "",
        "details": "new game",
        "board": [
            ["r", "n", "b", "q", "k", "b", "n", "r"],
            ["p", "p", "p", "p", "p", "p", "p", "p"],
            [" ", " ", " ", " ", " ", " ", " ", " "],
            [" ", " ", " ", " ", " ", " ", " ", " "],
            [" ", " ", " ", " ", " ", " ", " ", " "],
            [" ", " ", " ", " ", " ", " ", " ", " "],
            ["P", "P", "P", "P", "P", "P", "P", "P"],
            ["R", "N", "B", "Q", "K", "B", "N", "R"]
        ]
    }
]